TradernetPublicApiClient/__init__.py
PublicApiClient-0.1.3.2.dist-info/METADATA
PublicApiClient-0.1.3.2.dist-info/WHEEL
PublicApiClient-0.1.3.2.dist-info/top_level.txt
PublicApiClient-0.1.3.2.dist-info/zip-safe
PublicApiClient-0.1.3.2.dist-info/RECORD
