Metadata-Version: 2.1
Name: PublicApiClient
Version: 0.1.3.2
Summary: Tradernet API PublicApiClient lib for Python 3
Home-page: https://tradernet.com/tradernet-api/public-api-client
Author: Mr. TradeBot & Robotrader Jr; Kostikov Alex
Author-email: kostikov@tradernet.com
License: MIT
Platform: UNKNOWN
Requires-Python: >=3
